devkool/__init__.py
devkool/main.py
devkool/scanner.py
devkool-0.1.1.dist-info/LICENSE
devkool-0.1.1.dist-info/METADATA
devkool-0.1.1.dist-info/WHEEL
devkool-0.1.1.dist-info/entry_points.txt
devkool-0.1.1.dist-info/top_level.txt
devkool-0.1.1.dist-info/RECORD
