Metadata-Version: 2.2
Name: devkool
Version: 0.1.1
Summary: AI-Powered API Management CLI
Home-page: https://github.com/bumbum2403/Devkool_app
Author: Shubham Dwivedi
Author-email: sd.shubham2403@gmail.com
Keywords: api,management,testing,ai,cli,developer tools
Classifier: Development Status :: 3 - Alpha
Classifier: Intended Audience :: Developers
Classifier: Topic :: Software Development :: Libraries :: Python Modules
Classifier: License :: OSI Approved :: MIT License
Classifier: Programming Language :: Python :: 3
Classifier: Programming Language :: Python :: 3.7
Classifier: Programming Language :: Python :: 3.8
Classifier: Programming Language :: Python :: 3.9
Classifier: Programming Language :: Python :: 3.10
Classifier: Programming Language :: Python :: 3.11
License-File: LICENSE
Requires-Dist: typer
Requires-Dist: cryptography
Requires-Dist: transformers
Requires-Dist: requests
Requires-Dist: httpx
Requires-Dist: requests-toolbelt
Dynamic: author
Dynamic: author-email
Dynamic: classifier
Dynamic: description
Dynamic: description-content-type
Dynamic: home-page
Dynamic: keywords
Dynamic: requires-dist
Dynamic: summary
